provinces_and_cities/__init__.py
provinces_and_cities-1.0.4.dist-info/LICENSE
provinces_and_cities-1.0.4.dist-info/METADATA
provinces_and_cities-1.0.4.dist-info/WHEEL
provinces_and_cities-1.0.4.dist-info/top_level.txt
provinces_and_cities-1.0.4.dist-info/RECORD
