Metadata-Version: 2.2
Name: provinces-and-cities
Version: 1.0.4
Summary: Package of countries provinces and cities.
Home-page: https://github.com/mohammad-prb/provinces-and-cities-pypi
Author: Mohammad Pourbehzad
Author-email: Mohammad Pourbehzad <pspipm27@gmail.com>
License: Copyright (c) 2024 The Python Packaging Authority
Project-URL: Homepage, https://github.com/mohammad-prb/provinces-and-cities-pypi
Project-URL: Issues, https://github.com/mohammad-prb/provinces-and-cities-pypi/issues
Project-URL: Repository, https://github.com/mohammad-prb/provinces-and-cities-pypi.git
Keywords: provinces,province,cities,city,iran,germany
Classifier: Programming Language :: Python :: 3
Classifier: License :: OSI Approved :: MIT License
Classifier: Operating System :: OS Independent
Requires-Python: >=3.6
License-File: LICENSE
Dynamic: author
Dynamic: home-page
Dynamic: requires-python
